setup.py
ajilog/__init__.py
ajilog/core.py
ajilog/settings.py
ajilog.egg-info/PKG-INFO
ajilog.egg-info/SOURCES.txt
ajilog.egg-info/dependency_links.txt
ajilog.egg-info/requires.txt
ajilog.egg-info/top_level.txt
tests/__init__.py
tests/conf.py
tests/test_custom_names.py
tests/test_escape_codes.py
tests/test_names.py
tests/test_repr.py
tests/test_settings.py