Metadata-Version: 1.0
Name: ajilog
Version: 0.0.4.1
Summary: Wrapper for colorlog for better use.
Home-page: UNKNOWN
Author: Aji Liu
Author-email: amigcamel@gmail.com
License: UNKNOWN
Platform: UNKNOWN
